<?xml version="1.0" encoding="utf-8" ?>
<dwsync>
<file name="bootstrap.min.css" server="140.117.240.246//var/www/html/246/lin/try/" local="131281657700000000" remote="131350750200000000" Dst="0" />
<file name="bootstrap-grid.min.css" server="140.117.240.246//var/www/html/246/lin/try/" local="131281657700000000" remote="131350750200000000" Dst="0" />
<file name="bootstrap-grid.min.css.map" server="140.117.240.246//var/www/html/246/lin/try/" local="131281657700000000" remote="131350750200000000" Dst="0" />
<file name="bootstrap-reboot.min.css" server="140.117.240.246//var/www/html/246/lin/try/" local="131281657700000000" remote="131350750200000000" Dst="0" />
<file name="bootstrap-reboot.min.css.map" server="140.117.240.246//var/www/html/246/lin/try/" local="131281657700000000" remote="131350750200000000" Dst="0" />
<file name="bootstrap.min.css.map" server="140.117.240.246//var/www/html/246/lin/try/" local="131281657700000000" remote="131350750200000000" Dst="0" />
<file name="style.css" server="140.117.240.246//var/www/html/246/lin/try/" local="131352523397748389" remote="131350766400000000" Dst="0" />
<file name="mdb.min.css" server="140.117.240.246//var/www/html/246/lin/try/" local="131352523398343811" remote="131350766400000000" Dst="0" />
</dwsync>